trunofficial/__init__.py
trunofficial/trunofficial.py
trunofficial-0.2.4.dist-info/DESCRIPTION.rst
trunofficial-0.2.4.dist-info/METADATA
trunofficial-0.2.4.dist-info/RECORD
trunofficial-0.2.4.dist-info/WHEEL
trunofficial-0.2.4.dist-info/entry_points.txt
trunofficial-0.2.4.dist-info/metadata.json
trunofficial-0.2.4.dist-info/top_level.txt
