Metadata-Version: 2.0
Name: trunofficial
Version: 0.2.4
Summary: Unofficial API to the Truecaller phone number search
Home-page: https://www.github.com/ritiek/trunofficial
Author: Ritiek Malhotra
Author-email: ritiekmalhotra123@gmail.com
License: MIT
Download-URL: https://github.com/ritiek/trunofficial/archive/v0.2.4.tar.gz
Keywords: truecaller,search,python,unofficial,api
Platform: UNKNOWN
